Digital ASIC Frontend Flow/Sequential/D Flip Flop/dff.v
module dff(q,data,clk,rst);
output reg q;
input data,clk,rst;
always @(posedge clk or posedge rst)
begin
    if(rst)
	q<=1'b0;
    else
	q<=data;
end
endmodule

Digital ASIC Frontend Flow/Sequential/D Flip Flop/dff_tb.v
`timescale 1ns/1ps

module dff_tb;
    // 1. Creating registers for inputs and a wire for the output
   reg test_clk;
   reg test_rst;
   reg test_data;
   wire test_q;

   // 2. Instantiating the actual D Flip Flop module (connect pins)
   dff uut (
	.q(test_q),
	.clk(test_clk),
	.rst(test_rst),
	.data(test_data)
	);

   // 3. Generating a clock, test_clk changes every 5 ns, so time-period of clock = 10 ns
    always #5 test_clk = ~test_clk;

  // 4. Generating the input signals over time
   initial begin
        // Telling iverilog to dump waveform data for GTKWave
	$dumpfile("simulation.vcd");
	$dumpvars(0, dff_tb);

  // 5. Initial condition
        test_clk  = 0;
        test_rst  = 1;

        // Test Case 1: while D Flip Flop is in asynchronous reset, setting data = 0 and then data = 1
	test_data = 0; #10
	test_data = 1; #10

        // Test Case 2: Setting data = 1 before a rising clock edge
	test_rst = 0; #10;
        test_data = 1; #10;

        // Test Case 3: Changing data to 0 before the next rising edge
        test_data = 0; #10;

        // Test Case 4: Setting data = 1 again
        test_data = 1; #10;

        // Test Case 5: Resetting instantly while clock is running
        test_rst = 1; #10

        // Test Case 6: While reset is active, let's give data = 0
       	test_data = 0;
	
	$finish; // End simulation
end
endmodule

Digital ASIC Frontend Flow/Sequential/D Flip Flop/simulation.vcd
$date
	Mon Aug 17 19:24:02 2026
$end
$version
	Icarus Verilog
$end
$timescale
	1ps
$end
$scope module dff_tb $end
$var wire 1 ! test_q $end
$var reg 1 " test_clk $end
$var reg 1 # test_data $end
$var reg 1 $ test_rst $end
$scope module uut $end
$var wire 1 " clk $end
$var wire 1 # data $end
$var wire 1 $ rst $end
$var reg 1 ! q $end
$upscope $end
$upscope $end
$enddefinitions $end
$comment Show the parameter values. $end
$dumpall
$end
#0
$dumpvars
1$
0#
0"
0!
$end
#5000
1"
#10000
0"
1#
#15000
1"
#20000
0"
0$
#25000
1!
1"
#30000
0"
#35000
1"
#40000
0"
0#
#45000
0!
1"
#50000
0"
1#
#55000
1!
1"
#60000
0!
0"
1$
#65000
1"
#70000
0"
0#
